pyplanetarium-0.2.1.dist-info/METADATA
pyplanetarium-0.2.1.dist-info/WHEEL
pyplanetarium-0.2.1.dist-info/license_files/LICENSE
pyplanetarium/__init__.py
pyplanetarium/__init__.pyi
pyplanetarium/py.typed
pyplanetarium/pyplanetarium.abi3.so
pyplanetarium-0.2.1.dist-info/RECORD
