Metadata-Version: 2.1
Name: pyplanetarium
Version: 0.2.1
Classifier: Development Status :: 4 - Beta
Classifier: Intended Audience :: Science/Research
Classifier: License :: OSI Approved :: MIT License
Classifier: Programming Language :: Rust
Classifier: Programming Language :: Python :: Implementation :: CPython
Classifier: Topic :: Scientific/Engineering :: Astronomy
Classifier: Topic :: Scientific/Engineering :: Visualization
Classifier: Topic :: Software Development :: Libraries :: Python Modules
Classifier: Typing :: Typed
License-File: LICENSE
Summary: Python bindings for Rust Planetarium rendering library
Keywords: astronomy,simulation,python
Author: Sergey Kvachonok <ravenexp@gmail.com>
Author-email: Sergey Kvachonok <ravenexp@gmail.com>
License: MIT
Requires-Python: >=3.7
Project-URL: Source Code, https://github.com/ravenexp/pyplanetarium
